{"is_source_file": true, "format": "JavaScript/JSX", "description": "React functional component for a contact form with validation, utilizing react-hook-form and Zod schema validation.", "external_files": ["./Alert", "../utils/validators"], "external_methods": ["useForm", "zodResolver"], "published": ["default"], "classes": [], "methods": [{"name": "ContactForm({ onSubmit, submitting = false, serverError, serverSuccess })", "description": "React functional component implementing contact form with validation, handling form submission and displaying success/error alerts.", "scope": "", "scopeKind": ""}], "calls": ["useForm", "zodResolver", "register", "handleSubmit", "errors.<field>.message", "Alert"], "search-terms": ["ContactForm", "react-hook-form", "ZodSchema", "form validation", "React component", "contact form"], "state": 2, "file_id": 34, "knowledge_revision": 77, "git_revision": "", "ctags": [{"_type": "tag", "name": "ContactForm", "path": "/home/kavia/workspace/code-generation/classical-dance-teacher-portfolio-198096-198110/frontend/src/components/ContactForm.jsx", "pattern": "/^export default function ContactForm({ onSubmit, submitting = false, serverError, serverSuccess }/", "language": "JavaScript", "kind": "function", "signature": "({ onSubmit, submitting = false, serverError, serverSuccess })"}], "hash": "fcb63dd0bbcbe42ae9f1e31f1c6edd7b", "format-version": 4, "code-base-name": "frontend", "filename": "frontend/src/components/ContactForm.jsx", "revision_history": [{"77": ""}]}