{"is_source_file": true, "format": "jsx", "description": ".jsx file: main.jsx", "external_files": [], "external_methods": [], "published": [], "classes": [], "methods": [], "calls": [], "search-terms": ["main.jsx", "jsx"], "state": 2, "file_id": 4, "knowledge_revision": 88, "git_revision": "cf38ba2095c99d404b67961fe390001a9baf2616", "revision_history": [{"10": ""}, {"88": "cf38ba2095c99d404b67961fe390001a9baf2616"}], "ctags": [], "filename": "frontend/src/main.jsx", "format-version": 4, "code-base-name": "https://github.com/kavia-common/classical-dance-teacher-portfolio-198096-198110.git:kavia-main"}